iSATex/__init__.py
iSATex/const.py
iSATex/container.py
iSATex/control.py
iSATex/core.py
iSATex/defaultdecodefunction.py
iSATex/defaultencodefunction.py
iSATex/defaultevent.py
iSATex/defaultmappingfunction.py
iSATex/defaultmenuitem.py
iSATex/defaultpanel.py
iSATex/defaultpeakfunction.py
iSATex/defaultspectrumfunction.py
iSATex/main.py
iSATex/manager.py
iSATex/objects.py
iSATex/util.py
iSATex-0.0.4.dist-info/LICENSE.rst
iSATex-0.0.4.dist-info/METADATA
iSATex-0.0.4.dist-info/WHEEL
iSATex-0.0.4.dist-info/top_level.txt
iSATex-0.0.4.dist-info/RECORD
