Metadata-Version: 2.1
Name: iSATex
Version: 0.0.4
Summary: GUI based software for bunch spectral data analysis
Home-page: https://github.com/ryoTd0112/iSATex
Author: Ryo Tandai
Author-email: ryo.s1042@gmail.com
Maintainer: RyoTandai
Maintainer-email: ryo.s1042@gmail.com
License: BSD-3-Clause
Keywords: Spectrum,GUI
Platform: UNKNOWN
Classifier: License :: OSI Approved :: BSD License
Classifier: Programming Language :: Python
Classifier: Programming Language :: Python :: 3
Classifier: Topic :: Software Development :: Libraries :: Python Modules
Requires-Dist: cycler (==0.10.0)
Requires-Dist: keyboard (==0.13.5)
Requires-Dist: kiwisolver (==1.3.1)
Requires-Dist: matplotlib (==3.3.3)
Requires-Dist: numpy (==1.19.5)
Requires-Dist: Pillow (==8.1.0)
Requires-Dist: pyparsing (==2.4.7)
Requires-Dist: python-dateutil (==2.8.1)
Requires-Dist: scipy (==1.6.0)
Requires-Dist: six (==1.15.0)
Requires-Dist: wxPython (==4.1.1)
